<ParaViewReaders>
  <Reader name="H5Part"
          extensions="h5part h5Part"
          file_description="H5Part HDF5 particle files">
  </Reader>
  <Reader name="H5SPH"
          extensions="h5sph"
          file_description="H5SPH HDF5 particle files">
  </Reader>
  <Reader name="PTipsyReader"
			extensions="std"
			file_description="Tipsy Binary (Parallel)">
  </Reader>
  <Reader name="TipsyReader"
			extensions="std"
			file_description="Tipsy Binary">
	</Reader>
  <Reader name="CustomProbeReader"
			extensions="probe"
			file_description="Probe file for use with SPH/meshless filters">
  </Reader>

</ParaViewReaders>